{"K_ID":{"0":1,"1":2,"2":3,"3":4,"4":5,"5":6,"6":7,"7":8,"8":9,"9":10,"10":11,"11":12,"12":13,"13":14,"14":15,"15":16,"16":17,"17":18,"18":19,"19":20,"20":21,"21":22},"Klinikname":{"0":"Augenklinik Dr.Hoffmann","1":"Krankenhaus Marienstift Braunschweig","2":"Herzogin Elisabeth Hospital Braunschweig","3":"Asklepios Fachklinikum G\u00f6ttingen","4":"Asklepios Fachklinikum Tiefenbrunn","5":"Friederikenstift Hannover","6":"Annastift Hannover","7":"Clementinenhaus","8":"Sophienklinik Hannover","9":"KRH Klinikum Gro\u00dfburgwedel","10":"KRH Klinikum Lehrte","11":"Krankenhaus Lindenbrunn","12":"Krankenhaus Hameln","13":"AMEOS Klinikum Alfeld","14":"Helios Klinikum Hildesheim","15":"Helios Klinikum Cuxhaven","16":"OsteMed Klinik Bremerv\u00f6rde","17":"Klinik Fallingborstel","18":"Klinikum Emden","19":"Krankenhaus Ludmillenstift","20":"Marienhospital Papenburg","21":"Kreiskrankenhaus Osterholz"},"Link Google Maps":{"0":"https:\/\/www.google.com\/maps\/place\/Augenklinik+Dr.+Hoffmann\/@52.2555789,10.5275976,15z\/data=!4m2!3m1!1s0x0:0xe66ee9e189648187?sa=X&ved=2ahUKEwiUrOzD5_DuAhVLDOwKHUVOACkQ_BIwDHoECBgQBQ","1":"https:\/\/www.google.com\/maps\/place\/Krankenhaus+Marienstift+gGmbH\/@52.2584042,10.5452332,15z\/data=!4m2!3m1!1s0x0:0x2f02bc5a88d3c4a4?sa=X&ved=2ahUKEwiaitH85_DuAhXEwQIHHblHCPkQ_BIwCnoECBUQBQ","2":"https:\/\/www.google.com\/maps\/place\/Herzogin+Elisabeth+Hospital\/@52.2329937,10.5267147,15z\/data=!4m2!3m1!1s0x0:0x66131345a9ba3dfe?sa=X&ved=2ahUKEwjDndeY6PDuAhUOwKQKHQttAAkQ_BIwDXoECBoQBQ","3":"https:\/\/www.google.com\/maps\/place\/Asklepios+Fachklinikum+G%C3%B6ttingen\/@51.5241467,9.916557,15z\/data=!4m5!3m4!1s0x0:0xa2869d54b7ca1a8a!8m2!3d51.5241467!4d9.916557","4":"https:\/\/www.google.com\/maps\/place\/Asklepios+Fachklinikum+Tiefenbrunn\/@51.498851,9.8716437,15z\/data=!4m2!3m1!1s0x0:0xd7525199e92be7b?sa=X&ved=2ahUKEwiLwKW37PDuAhVCC-wKHb2GAFwQ_BIwDXoECBcQBQ","5":"https:\/\/www.google.com\/maps\/place\/DIAKOVERE+Friederikenstift\/@52.3712581,9.7241985,15z\/data=!4m2!3m1!1s0x0:0x2562020c6992a2f5?sa=X&ved=2ahUKEwjz4Mm_7PDuAhUJOuwKHfjwDoYQ_BIwDXoECBkQBQ","6":"https:\/\/www.google.com\/maps\/place\/DIAKOVERE+Annastift\/@52.3697126,9.8095478,15z\/data=!4m2!3m1!1s0x0:0xcda40e96bf4ee3b5?sa=X&ved=2ahUKEwju-snN7PDuAhUH3KQKHTmUADsQ_BIwCnoECB0QBQ","7":"https:\/\/www.google.com\/maps\/place\/DRK-Krankenhaus+Clementinenhaus\/@52.3867053,9.7451748,15z\/data=!4m2!3m1!1s0x0:0xc26fce799779eb2a?sa=X&ved=2ahUKEwi5nJDV7PDuAhUEwQIHHSapBl4Q_BIwCnoECBcQBQ","8":"https:\/\/www.google.com\/maps\/place\/Sophienklinik+GmbH\/@52.3622984,9.7773725,15z\/data=!4m2!3m1!1s0x0:0xa5f9e423a2b06584?sa=X&ved=2ahUKEwiDzZqV7fDuAhWKtqQKHdBRAK4Q_BIwDXoECBkQBQ","9":"https:\/\/www.google.com\/maps\/place\/KRH+Klinikum+Gro%C3%9Fburgwedel\/@52.49634,9.86174,15z\/data=!4m2!3m1!1s0x0:0x6097ffe5c867564f?sa=X&ved=2ahUKEwiX7YOl7fDuAhXEDOwKHXe_Ax4Q_BIwFnoECCEQBQ","10":"https:\/\/www.google.com\/maps\/place\/KRH+Klinikum+Lehrte\/@52.37997,9.9836,15z\/data=!4m2!3m1!1s0x0:0xcdad104f265200f7?sa=X&ved=2ahUKEwjPteLO7fDuAhWOzaQKHaAUCiMQ_BIwDnoECBYQBQ","11":"https:\/\/www.google.com\/maps\/place\/Krankenhaus+Lindenbrunn\/@52.1096994,9.5498324,15z\/data=!4m2!3m1!1s0x0:0x2ba194a9d9fbed1d?sa=X&ved=2ahUKEwiqp6iV7_DuAhWN16QKHRgrBg0Q_BIwDXoECBYQBQ","12":"https:\/\/www.google.com\/maps\/place\/Sana+Klinikum+Hameln-Pyrmont\/@52.1072071,9.3519386,15z\/data=!4m2!3m1!1s0x0:0x38c5edd92206a8ed?sa=X&ved=2ahUKEwigqvKp7_DuAhXVOuwKHcvCCogQ_BIwDXoECBoQBQ","13":"https:\/\/www.google.com\/maps\/place\/AMEOS+Klinikum+Alfeld\/@51.9942339,9.8324207,15z\/data=!4m2!3m1!1s0x0:0xae524284e15399f3?sa=X&ved=2ahUKEwiI24i57_DuAhXGuaQKHcSQAesQ_BIwDHoECBkQBQ","14":"https:\/\/www.google.com\/maps\/place\/Helios+Klinikum+Hildesheim\/@52.15131,9.9766266,15z\/data=!4m2!3m1!1s0x0:0x6f9974ba52e7ae71?sa=X&ved=2ahUKEwick53v7_DuAhWPG-wKHeLfAwkQ_BIwDXoECBcQBQ","15":"https:\/\/www.google.com\/maps\/place\/HELIOS+Klinik+Cuxhaven\/@53.8528608,8.6921898,15z\/data=!4m2!3m1!1s0x0:0x3a2fe1f38b90ded1?sa=X&ved=2ahUKEwjA0ofu8PDuAhVCPuwKHV3mAX0Q_BIwCnoECBkQBQ","16":"https:\/\/www.google.com\/maps\/place\/OsteMed+Klinik+Bremerv%C3%B6rde\/@53.47135,9.13539,15z\/data=!4m2!3m1!1s0x0:0x9e67a0479524aff6?sa=X&ved=2ahUKEwjbvs7z8fDuAhXaOewKHb8_C-cQ_BIwDXoECBgQBQ","17":"https:\/\/www.google.com\/maps\/place\/Klinik+Fallingbostel\/@52.86903,9.7059601,15z\/data=!4m2!3m1!1s0x0:0xdc98c5fc80626f15?sa=X&ved=2ahUKEwiYmdaV8vDuAhWCHewKHabKBksQ_BIwE3oECB8QBQ","18":"https:\/\/www.google.com\/maps\/place\/Klinikum+Emden+-+Hans-Susemihl-Krankenhaus\/@53.3754445,7.2129241,15z\/data=!4m2!3m1!1s0x0:0x5db7edd86596419e?sa=X&ved=2ahUKEwiDpfyV9PDuAhWCjaQKHWgBCcwQ_BIwD3oECCMQBQ","19":"https:\/\/www.google.com\/maps\/place\/Krankenhaus+Ludmillenstift\/@52.688896,7.2928619,15z\/data=!4m2!3m1!1s0x0:0x59c2048e1a4953f?sa=X&ved=2ahUKEwigpYag9vDuAhWxwAIHHXwPDugQ_BIwDXoECBYQBQ","20":"https:\/\/www.google.com\/maps\/place\/Marienkrankenhaus+Papenburg-+Aschendorf+GmbH+Betriebsst%C3%A4tte+Aschendorf\/@53.05092,7.3292999,15z\/data=!4m5!3m4!1s0x0:0x20891ebe2b01a054!8m2!3d53.05092!4d7.3292999","21":"https:\/\/www.google.com\/maps\/place\/Kreiskrankenhaus+Osterholz\/@53.2337217,8.7942051,15z\/data=!4m2!3m1!1s0x0:0xee4b35384cb3b2ad?sa=X&ved=2ahUKEwjYrbHu8fDuAhVRyaQKHSREAa0Q_BIwDXoECBYQBQ"},"Link Klinikbewertungen":{"0":"https:\/\/www.klinikbewertungen.de\/klinik-forum\/erfahrung-mit-augenklinik-dr-hoffmann-braunschweig","1":"https:\/\/www.klinikbewertungen.de\/klinik-forum\/erfahrung-mit-krankenhaus-marienstift-braunschweig","2":"https:\/\/www.klinikbewertungen.de\/klinik-forum\/erfahrung-mit-kliniken-herzogin-elisabeth-braunschweig","3":"https:\/\/www.klinikbewertungen.de\/klinik-forum\/erfahrung-mit-krankenhaus-goettingen","4":"https:\/\/www.klinikbewertungen.de\/klinik-forum\/erfahrung-mit-krankenhaus-tiefenbrunn-rosdorf","5":"https:\/\/www.klinikbewertungen.de\/klinik-forum\/erfahrung-mit-krankenhaus-friederikenstift-hannover","6":"https:\/\/www.klinikbewertungen.de\/klinik-forum\/erfahrung-mit-annastift-hannover","7":"https:\/\/www.klinikbewertungen.de\/klinik-forum\/erfahrung-mit-drk-clementinenhaus-hannover","8":"https:\/\/www.klinikbewertungen.de\/klinik-forum\/erfahrung-mit-sophien-klinik-hannover","9":"https:\/\/www.klinikbewertungen.de\/klinik-forum\/erfahrung-mit-krankenhaus-grossburgwedel","10":"https:\/\/www.klinikbewertungen.de\/klinik-forum\/erfahrung-mit-krankenhaus-lehrte","11":"https:\/\/www.klinikbewertungen.de\/klinik-forum\/erfahrung-mit-krankenhaus-lindenbrunn-coppenbruegge","12":"https:\/\/www.klinikbewertungen.de\/klinik-forum\/erfahrung-mit-krankenhaus-hameln","13":"https:\/\/www.klinikbewertungen.de\/klinik-forum\/erfahrung-mit-kreis-und-stadtkrankenhaus-alfeld","14":"https:\/\/www.klinikbewertungen.de\/klinik-forum\/erfahrung-mit-krankenhaus-hildesheim","15":"https:\/\/www.klinikbewertungen.de\/klinik-forum\/erfahrung-mit-stadtkrankenhaus-cuxhaven","16":"https:\/\/www.klinikbewertungen.de\/klinik-forum\/erfahrung-mit-krankenhaus-bremervoerde","17":"https:\/\/www.klinikbewertungen.de\/klinik-forum\/erfahrung-mit-klinik-fallingbostel","18":"https:\/\/www.klinikbewertungen.de\/klinik-forum\/erfahrung-mit-klinikum-emden","19":"https:\/\/www.klinikbewertungen.de\/klinik-forum\/erfahrung-mit-krankenhaus-ludmillenstift-meppen","20":"https:\/\/www.klinikbewertungen.de\/klinik-forum\/erfahrung-mit-marienhospital-papenburg","21":"https:\/\/www.klinikbewertungen.de\/klinik-forum\/erfahrung-mit-krankenhaus-osterholz-scharmbeck"}}